devpi_keycloak/__init__.py
devpi_keycloak/entrypoint.py
devpi_keycloak-0.0.1.dist-info/LICENSE.txt
devpi_keycloak-0.0.1.dist-info/METADATA
devpi_keycloak-0.0.1.dist-info/WHEEL
devpi_keycloak-0.0.1.dist-info/entry_points.txt
devpi_keycloak-0.0.1.dist-info/top_level.txt
devpi_keycloak-0.0.1.dist-info/RECORD
