Metadata-Version: 2.1
Name: devpi-keycloak
Version: 0.0.1
Summary: Devpi plugin to auth via Keycloak SSO service
Home-page: http://github.com/turbokadi/devpi-keycloak
Author: MoJoh
Author-email: cryptoweirdo@protonmail.com
License: MIT
Keywords: devpi keycloak auth module
Platform: any
Classifier: Development Status :: 3 - Alpha
Classifier: Intended Audience :: System Administrators
Classifier: License :: OSI Approved :: MIT License
Classifier: Topic :: Software Development :: Libraries :: Python Modules
Classifier: Topic :: Internet
License-File: LICENSE.txt
Requires-Dist: devpi-server (>=4.0.0)
Requires-Dist: keycloak-basic (>=1.2.1)
